Metadata-Version: 2.1
Name: libxbydragon
Version: 0.0.2
Summary: A very basic calculator virson 0.0.2
Home-page: UNKNOWN
Author: yassen waly
Author-email: 
License: MIT
Keywords: calculator
Platform: UNKNOWN
Classifier: Development Status :: 5 - Production/Stable
Classifier: Intended Audience :: Education
Classifier: Operating System :: Microsoft :: Windows :: Windows 10
Classifier: License :: OSI Approved :: MIT License
Classifier: Programming Language :: Python :: 3
License-File: LICENCE.txt
